comokit4py/__init__.py
comokit4py/comokit2png.py
comokit4py/generateMultipleXML.py
comokit4py/generateSBatchFiles.py
comokit4py-0.1.0.dist-info/LICENSE
comokit4py-0.1.0.dist-info/METADATA
comokit4py-0.1.0.dist-info/WHEEL
comokit4py-0.1.0.dist-info/top_level.txt
comokit4py-0.1.0.dist-info/RECORD
