Metadata-Version: 2.1
Name: comokit4py
Version: 0.1.0
Summary: Python3 library to simplify the exploration of COMOKIT
Home-page: https://github.com/COMOKIT/comokit4py
Author: COMOKIT
Author-email: contact@comokit.org
License: UNKNOWN
Platform: UNKNOWN
Classifier: Programming Language :: Python :: 3
Classifier: License :: OSI Approved :: GNU Library or Lesser General Public License (LGPL)
Classifier: Operating System :: OS Independent
Classifier: Intended Audience :: Science/Research
Classifier: Programming Language :: Other
Classifier: Topic :: Scientific/Engineering
Requires-Python: >=3.6
